LICENSE
MANIFEST.in
README.md
package.json
setup.py
dash_pane_split/DashPaneSplit.py
dash_pane_split/__init__.py
dash_pane_split/_imports_.py
dash_pane_split/dash_pane_split.min.js
dash_pane_split/dash_pane_split.min.js.map
dash_pane_split/metadata.json
dash_pane_split/package-info.json
dash_pane_split.egg-info/PKG-INFO
dash_pane_split.egg-info/SOURCES.txt
dash_pane_split.egg-info/dependency_links.txt
dash_pane_split.egg-info/top_level.txt
tests/test_usage.py