Metadata-Version: 2.1
Name: dash-pane-split
Version: 0.1.6
Summary: Dash PaneSplit allows the page area to be split into Main and Sidebar sections. By combining multiple PaneSplits, a complex and flexible experience similar to Studio style can be achieved.
Author: mapix <mapix.me@gmail.com>
License: MIT
Classifier: Framework :: Dash
License-File: LICENSE
